[
  {
    "provider_id": "agirls",
    "provider_name": "电獭少女",
    "route_key": "/topic_list",
    "route": {
      "name": "当前精选主题列表",
      "path": "/topic_list",
      "example": "/agirls/topic_list",
      "parameters": {},
      "description": ""
    }
  },
  {
    "provider_id": "agirls",
    "provider_name": "电獭少女",
    "route_key": "/topic/:topic",
    "route": {
      "name": "精选主题",
      "path": "/topic/:topic",
      "example": "/agirls/topic/AppleWatch",
      "parameters": {
        "topic": "精选主题，可通过下方精选主题列表获得"
      },
      "description": ""
    }
  },
  {
    "provider_id": "agirls",
    "provider_name": "电獭少女",
    "route_key": "/:category?",
    "route": {
      "name": "分类",
      "path": "/:category?",
      "example": "/agirls/app",
      "parameters": {
        "category": "分类，默认为最新文章，可在对应主题页的 URL 中找到，下表仅列出部分"
      },
      "description": "| App 评测 | 手机开箱 | 笔电开箱 | 3C 周边     | 教学小技巧 | 科技情报 |\n| -------- | -------- | -------- | ----------- | ---------- | -------- |\n| app      | phone    | computer | accessories | tutorial   | techlife |"
    }
  },
  {
    "provider_id": "aibase",
    "provider_name": "AIbase",
    "route_key": "/news",
    "route": {
      "name": "资讯",
      "path": "/news",
      "example": "/aibase/news",
      "parameters": {},
      "description": "获取 AI 资讯列表"
    }
  },
  {
    "provider_id": "ainvest",
    "provider_name": "AInvest",
    "route_key": "/news",
    "route": {
      "name": "Latest News",
      "path": "/news",
      "example": "/ainvest/news",
      "parameters": {},
      "description": ""
    }
  },
  {
    "provider_id": "aliresearch",
    "provider_name": "阿里研究院",
    "route_key": "/information/:type?",
    "route": {
      "name": "资讯",
      "path": "/information/:type?",
      "example": "/aliresearch/information",
      "parameters": {
        "type": "类型，见下表，默认为新闻"
      },
      "description": "| 新闻 | 观点 | 案例 |\n| ---- | ---- | ---- |"
    }
  },
  {
    "provider_id": "apple",
    "provider_name": "Apple",
    "route_key": "/apps/update/:country/:id/:platform?",
    "route": {
      "name": "App Update",
      "path": "/apps/update/:country/:id/:platform?",
      "example": "/apple/apps/update/us/id408709785",
      "parameters": {
        "country": "App Store Country, obtain from the app URL, see below",
        "id": "App id, obtain from the app URL",
        "platform": {
          "description": "App Platform, see below, all by default",
          "options": [
            {
              "value": "All",
              "label": "all"
            },
            {
              "value": "iOS",
              "label": "iOS"
            },
            {
              "value": "macOS",
              "label": "macOS"
            },
            {
              "value": "tvOS",
              "label": "tvOS"
            }
          ]
        }
      },
      "description": "\n::: tip\n  For example, the URL of [GarageBand](https://apps.apple.com/us/app/messages/id408709785) in the App Store is `https://apps.apple.com/us/app/messages/id408709785`. In this case, the `App Store Country` parameter for the route is `us`, and the `App id` parameter is `id1146560473`. So the route should be [`/apple/apps/update/us/id408709785`](https://rsshub.app/apple/apps/update/us/id408709785).\n:::"
    }
  },
  {
    "provider_id": "baidu",
    "provider_name": "百度",
    "route_key": "/gushitong/index",
    "route": {
      "name": "首页指数",
      "path": "/gushitong/index",
      "example": "/baidu/gushitong/index",
      "parameters": {},
      "description": ""
    }
  },
  {
    "provider_id": "behance",
    "provider_name": "Behance",
    "route_key": "/:user/:type?",
    "route": {
      "name": "User Works",
      "path": "/:user/:type?",
      "example": "/behance/mishapetrick",
      "parameters": {
        "user": "username",
        "type": {
          "description": "type",
          "options": [
            {
              "value": "projects",
              "label": "projects"
            },
            {
              "value": "appreciated",
              "label": "appreciated"
            }
          ],
          "default": "projects"
        }
      },
      "description": "Behance user's profile URL, like [https://www.behance.net/mishapetrick](https://www.behance.net/mishapetrick) the username will be `mishapetrick`。"
    }
  },
  {
    "provider_id": "bilibili",
    "provider_name": "哔哩哔哩 bilibili",
    "route_key": "/ranking/:rid_index?/:embed?/:redirect1?/:redirect2?",
    "route": {
      "name": "排行榜",
      "path": "/ranking/:rid_index?/:embed?/:redirect1?/:redirect2?",
      "example": "/bilibili/ranking/0",
      "parameters": {
        "rid_index": {
          "description": "排行榜分区 id 序号",
          "default": "0",
          "options": [
            {
              "value": "0",
              "label": "全站"
            },
            {
              "value": "3",
              "label": "国创相关"
            },
            {
              "value": "5",
              "label": "动画"
            },
            {
              "value": "6",
              "label": "音乐"
            },
            {
              "value": "7",
              "label": "舞蹈"
            },
            {
              "value": "8",
              "label": "游戏"
            },
            {
              "value": "9",
              "label": "知识"
            },
            {
              "value": "10",
              "label": "科技"
            },
            {
              "value": "11",
              "label": "运动"
            },
            {
              "value": "12",
              "label": "汽车"
            },
            {
              "value": "13",
              "label": "生活"
            },
            {
              "value": "14",
              "label": "美食"
            },
            {
              "value": "15",
              "label": "动物圈"
            },
            {
              "value": "16",
              "label": "鬼畜"
            },
            {
              "value": "17",
              "label": "时尚"
            },
            {
              "value": "18",
              "label": "娱乐"
            },
            {
              "value": "19",
              "label": "影视"
            },
            {
              "value": "23",
              "label": "原创"
            },
            {
              "value": "24",
              "label": "新人"
            }
          ]
        },
        "embed": "默认为开启内嵌视频, 任意值为关闭",
        "redirect1": "留空，用于兼容之前的路由",
        "redirect2": "留空，用于兼容之前的路由"
      },
      "description": ""
    }
  },
  {
    "provider_id": "bilibili",
    "provider_name": "哔哩哔哩 bilibili",
    "route_key": "/readlist/:listid",
    "route": {
      "name": "专栏文集",
      "path": "/readlist/:listid",
      "example": "/bilibili/readlist/25611",
      "parameters": {
        "listid": "文集 id, 可在专栏文集 URL 中找到"
      },
      "description": ""
    }
  },
  {
    "provider_id": "bookfere",
    "provider_name": "书伴",
    "route_key": "/:category",
    "route": {
      "name": "分类",
      "path": "/:category",
      "example": "/bookfere/skills",
      "parameters": {
        "category": {
          "description": "分类名",
          "options": [
            {
              "value": "weekly",
              "label": "每周一书"
            },
            {
              "value": "skills",
              "label": "使用技巧"
            },
            {
              "value": "books",
              "label": "图书推荐"
            },
            {
              "value": "news",
              "label": "新闻速递"
            },
            {
              "value": "essay",
              "label": "精选短文"
            }
          ]
        }
      },
      "description": "| 每周一书 | 使用技巧 | 图书推荐 | 新闻速递 | 精选短文 |\n| -------- | -------- | -------- | -------- | -------- |\n| weekly   | skills   | books    | news     | essay    |"
    }
  },
  {
    "provider_id": "caixin",
    "provider_name": "财新博客",
    "route_key": "/latest",
    "route": {
      "name": "最新文章",
      "path": "/latest",
      "example": "/caixin/latest",
      "parameters": {},
      "description": "说明：此 RSS feed 会自动抓取财新网的最新文章，但不包含 FM 及视频内容。订阅用户可根据文档设置环境变量后，在url传入`fulltext=`以解锁全文。"
    }
  },
  {
    "provider_id": "chub",
    "provider_name": "Chub",
    "route_key": "/characters",
    "route": {
      "name": "Characters",
      "path": "/characters",
      "example": "/chub/characters",
      "parameters": {},
      "description": ""
    }
  },
  {
    "provider_id": "cuilingmag",
    "provider_name": "萃嶺网",
    "route_key": "/:category?",
    "route": {
      "name": "分类",
      "path": "/:category?",
      "example": "/cuilingmag",
      "parameters": {
        "category": "分类，默认为空，即全部，可在对应分类页 URL 中找到"
      },
      "description": "::: tip\n  若订阅 [#哲学·文明](https://www.cuilingmag.com/category/philosophy_civilization)，网址为 `https://www.cuilingmag.com/category/philosophy_civilization`。截取 `https://www.cuilingmag.com/category` 到末尾的部分 `philosophy_civilization` 作为参数填入，此时路由为 [`/cuilingmag/philosophy_civilization`](https://rsshub.app/cuilingmag/philosophy_civilization)。\n:::\n\n| 分类                                                                       | ID                                                                                |\n| -------------------------------------------------------------------------- | --------------------------------------------------------------------------------- |\n| [哲学 · 文明](https://www.cuilingmag.com/category/philosophy_civilization) | [philosophy_civilization](https://rsshub.app/cuilingmag/philosophy_civilization) |\n| [艺术 · 科技](https://www.cuilingmag.com/category/art_science)             | [art_science](https://rsshub.app/cuilingmag/art_science)                         |\n| [未来 · 生命](https://www.cuilingmag.com/category/future_life)             | [future_life](https://rsshub.app/cuilingmag/future_life)                         |\n| [行星智慧](https://www.cuilingmag.com/category/planetary_wisdom)           | [planetary_wisdom](https://rsshub.app/cuilingmag/planetary_wisdom)               |\n| [数字治理](https://www.cuilingmag.com/category/digital_governance)         | [digital_governance](https://rsshub.app/cuilingmag/digital_governance)           |\n| [Noema精选](https://www.cuilingmag.com/category/selected_noema)            | [selected_noema](https://rsshub.app/cuilingmag/selected_noema)                   |\n  "
    }
  },
  {
    "provider_id": "digitalcameraworld",
    "provider_name": "Digital Camera World",
    "route_key": "/news",
    "route": {
      "name": "News",
      "path": "/news",
      "example": "/digitalcameraworld/news",
      "parameters": {},
      "description": ""
    }
  },
  {
    "provider_id": "dlsite",
    "provider_name": "DLsite",
    "route_key": "/new/:type",
    "route": {
      "name": "Current Release",
      "path": "/new/:type",
      "example": "/dlsite/new/home",
      "parameters": {
        "type": {
          "description": "类型",
          "options": [
            {
              "value": "home",
              "label": "「DLsite 同人」"
            },
            {
              "value": "comic",
              "label": "「DLsite コミック」"
            },
            {
              "value": "soft",
              "label": "「DLsite PCソフト」"
            },
            {
              "value": "maniax",
              "label": "「DLsite 同人 - R18」"
            },
            {
              "value": "books",
              "label": "「DLsite 成年コミック - R18」"
            },
            {
              "value": "pro",
              "label": "「DLsite 美少女ゲーム」"
            },
            {
              "value": "girls",
              "label": "「DLsite 乙女」"
            },
            {
              "value": "bl",
              "label": "「DLsite BL」"
            }
          ]
        }
      },
      "description": "| Doujin | Comics | PC Games | Doujin (R18) | Adult Comics | H Games | Otome | BL |\n| ------ | ------ | -------- | ------------ | ------------ | ------- | ----- | -- |\n| home   | comic  | soft     | maniax       | books        | pro     | girls | bl |"
    }
  },
  {
    "provider_id": "dlsite",
    "provider_name": "DLsite",
    "route_key": "/ci-en/:id/article",
    "route": {
      "name": "Ci-en Creators' Article",
      "path": "/ci-en/:id/article",
      "example": "/dlsite/ci-en/7400/article",
      "parameters": {
        "id": "Creator id, can be found in URL"
      },
      "description": ""
    }
  },
  {
    "provider_id": "dn",
    "provider_name": "DN.com",
    "route_key": "/:language/news/:category?",
    "route": {
      "name": "News",
      "path": "/:language/news/:category?",
      "example": "/dn/en-us/news",
      "parameters": {
        "language": "Language, see below",
        "category": "Category, see below, The Latest by default"
      },
      "description": "#### Language\n\n| English | 中文  |\n| ------- | ----- |\n| en-us   | zh-cn |\n\n#### Category\n\n| English Category     | 中文分类 | Category id |\n| -------------------- | -------- | ----------- |\n| The Latest           | 最新     |             |\n| Industry Information | 行业资讯 | category-1  |\n| Knowledge            | 域名知识 | category-2  |\n| Investment           | 域名投资 | category-3  |"
    }
  },
  {
    "provider_id": "dockerhub",
    "provider_name": "Docker Hub",
    "route_key": "/build/:owner/:image/:tag?",
    "route": {
      "name": "Image New Build",
      "path": "/build/:owner/:image/:tag?",
      "example": "/dockerhub/build/diygod/rsshub/latest",
      "parameters": {
        "owner": "Image owner, the owner of the official image fills in the library, for example: /dockerhub/build/library/mysql",
        "image": "Image name",
        "tag": {
          "description": "Image tag",
          "default": "latest"
        }
      },
      "description": ""
    }
  },
  {
    "provider_id": "dongqiudi",
    "provider_name": "懂球帝",
    "route_key": "/result/:team",
    "route": {
      "name": "足球赛果",
      "path": "/result/:team",
      "example": "/dongqiudi/result/50001755",
      "parameters": {
        "team": "球队 id, 可在[懂球帝数据](https://www.dongqiudi.com/data)中找到"
      },
      "description": ""
    }
  },
  {
    "provider_id": "dongqiudi",
    "provider_name": "懂球帝",
    "route_key": "/special/:id",
    "route": {
      "name": "专题",
      "path": "/special/:id",
      "example": "/dongqiudi/special/41",
      "parameters": {
        "id": "专题 id, 可自行通过 https://www.dongqiudi.com/special/+数字匹配"
      },
      "description": "| 新闻大爆炸 | 懂球帝十佳球 | 懂球帝本周 MVP |\n| ---------- | ------------ | -------------- |\n| 41         | 52           | 53             |"
    }
  },
  {
    "provider_id": "dongqiudi",
    "provider_name": "懂球帝",
    "route_key": "/top_news/:id?",
    "route": {
      "name": "新闻",
      "path": "/top_news/:id?",
      "example": "/dongqiudi/top_news/1",
      "parameters": {
        "id": "类别 id，不填默认头条新闻"
      },
      "description": "| 头条 | 深度 | 闲情 | D 站 | 中超 | 国际 | 英超 | 西甲 | 意甲 | 德甲 |\n| ---- | ---- | ---- | ---- | ---- | ---- | ---- | ---- | ---- | ---- |\n| 1    | 55   | 37   | 219  | 56   | 120  | 3    | 5    | 4    | 6    |"
    }
  },
  {
    "provider_id": "economist",
    "provider_name": "The Economist",
    "route_key": "/espresso",
    "route": {
      "name": "Espresso",
      "path": "/espresso",
      "example": "/economist/espresso",
      "parameters": {},
      "description": ""
    }
  },
  {
    "provider_id": "epicgames",
    "provider_name": "Epic Games Store",
    "route_key": "/freegames/:locale?/:country?",
    "route": {
      "name": "Free games",
      "path": "/freegames/:locale?/:country?",
      "example": "/epicgames/freegames/en-US/US",
      "parameters": {
        "locale": {
          "description": "Locale",
          "default": "en-US"
        },
        "country": {
          "description": "Country",
          "default": "US"
        }
      },
      "description": ""
    }
  },
  {
    "provider_id": "eventernote",
    "provider_name": "Eventernote",
    "route_key": "/actors/:name/:id",
    "route": {
      "name": "声优活动及演唱会",
      "path": "/actors/:name/:id",
      "example": "/eventernote/actors/三森すずこ/2634",
      "parameters": {
        "name": "声优姓名",
        "id": "声优 ID"
      },
      "description": ""
    }
  },
  {
    "provider_id": "fantia",
    "provider_name": "Fantia",
    "route_key": "/search/:type?/:caty?/:period?/:order?/:rating?/:keyword?",
    "route": {
      "name": "Search",
      "path": "/search/:type?/:caty?/:period?/:order?/:rating?/:keyword?",
      "example": "/fantia/search/posts/all/daily",
      "parameters": {
        "type": {
          "description": "Type, see the table below, `posts` by default",
          "options": [
            {
              "value": "fanclubs",
              "label": "クリエイター"
            },
            {
              "value": "posts",
              "label": "投稿"
            },
            {
              "value": "products",
              "label": "商品"
            },
            {
              "value": "commissions",
              "label": "コミッション"
            }
          ],
          "default": "posts"
        },
        "caty": {
          "description": "Category, see the table below, can also be found in search page URL, `すべてのクリエイター` by default",
          "options": [
            {
              "value": "all",
              "label": "すべてのクリエイター"
            },
            {
              "value": "illust",
              "label": "イラスト"
            },
            {
              "value": "comic",
              "label": "漫画"
            },
            {
              "value": "cosplay",
              "label": "コスプレ"
            },
            {
              "value": "youtuber",
              "label": "YouTuber・配信者"
            },
            {
              "value": "vtuber",
              "label": "Vtuber"
            },
            {
              "value": "voice",
              "label": "音声作品・ASMR"
            },
            {
              "value": "voiceactor",
              "label": "声優・歌い手"
            },
            {
              "value": "idol",
              "label": "アイドル"
            },
            {
              "value": "anime",
              "label": "アニメ・映像・写真"
            },
            {
              "value": "3d",
              "label": "3D"
            },
            {
              "value": "game",
              "label": "ゲーム制作"
            },
            {
              "value": "music",
              "label": "音楽"
            },
            {
              "value": "novel",
              "label": "小説"
            },
            {
              "value": "doll",
              "label": "ドール"
            },
            {
              "value": "art",
              "label": "アート・デザイン"
            },
            {
              "value": "program",
              "label": "プログラム"
            },
            {
              "value": "handmade",
              "label": "創作・ハンドメイド"
            },
            {
              "value": "history",
              "label": "歴史・評論・情報"
            },
            {
              "value": "railroad",
              "label": "鉄道・旅行・ミリタリー"
            },
            {
              "value": "shop",
              "label": "ショップ"
            },
            {
              "value": "other",
              "label": "その他"
            }
          ],
          "default": "all"
        },
        "period": {
          "description": "Ranking period, see the table below, empty by default",
          "options": [
            {
              "value": "daily",
              "label": "デイリー"
            },
            {
              "value": "weekly",
              "label": "ウィークリー"
            },
            {
              "value": "monthly",
              "label": "マンスリー"
            },
            {
              "value": "all",
              "label": "全期間"
            }
          ],
          "default": ""
        },
        "order": {
          "description": "Sorting, see the table below, `更新の新しい順` by default",
          "options": [
            {
              "value": "updater",
              "label": "更新の新しい順"
            },
            {
              "value": "update_old",
              "label": "更新の古い順"
            },
            {
              "value": "newer",
              "label": "投稿の新しい順"
            },
            {
              "value": "create_old",
              "label": "投稿の古い順"
            },
            {
              "value": "popular",
              "label": "お気に入り数順"
            }
          ],
          "default": "updater"
        },
        "rating": {
          "description": "Rating, see the table below, `すべて` by default",
          "options": [
            {
              "value": "all",
              "label": "すべて"
            },
            {
              "value": "general",
              "label": "一般のみ"
            },
            {
              "value": "adult",
              "label": "R18 のみ"
            }
          ],
          "default": "all"
        },
        "keyword": "Keyword, empty by default"
      },
      "description": "Type\n\n| クリエイター | 投稿  | 商品     | コミッション |\n| ------------ | ----- | -------- | ------------ |\n| fanclubs     | posts | products | commissions  |\n\n  Category\n\n| 分类                   | 分类名     |\n| ---------------------- | ---------- |\n| イラスト               | illust     |\n| 漫画                   | comic      |\n| コスプレ               | cosplay    |\n| YouTuber・配信者       | youtuber   |\n| Vtuber                 | vtuber     |\n| 音声作品・ASMR         | voice      |\n| 声優・歌い手           | voiceactor |\n| アイドル               | idol       |\n| アニメ・映像・写真     | anime      |\n| 3D                     | 3d         |\n| ゲーム制作             | game       |\n| 音楽                   | music      |\n| 小説                   | novel      |\n| ドール                 | doll       |\n| アート・デザイン       | art        |\n| プログラム             | program    |\n| 創作・ハンドメイド     | handmade   |\n| 歴史・評論・情報       | history    |\n| 鉄道・旅行・ミリタリー | railroad   |\n| ショップ               | shop       |\n| その他                 | other      |\n\n  Ranking period\n\n| デイリー | ウィークリー | マンスリー | 全期間 |\n| -------- | ------------ | ---------- | ------ |\n| daily    | weekly       | monthly    | all    |\n\n  Sorting\n\n| 更新の新しい順 | 更新の古い順 | 投稿の新しい順 | 投稿の古い順 | お気に入り数順 |\n| -------------- | ------------ | -------------- | ------------ | -------------- |\n| updater        | update_old  | newer          | create_old  | popular        |\n\n  Rating\n\n| すべて | 一般のみ | R18 のみ |\n| ------ | -------- | -------- |\n| all    | general  | adult    |"
    }
  },
  {
    "provider_id": "fastbull",
    "provider_name": "FastBull",
    "route_key": "/express-news",
    "route": {
      "name": "News Flash",
      "path": "/express-news",
      "example": "/fastbull/express-news",
      "parameters": {},
      "description": ""
    }
  },
  {
    "provider_id": "followin",
    "provider_name": "Followin",
    "route_key": "/:categoryId?/:lang?",
    "route": {
      "name": "Home",
      "path": "/:categoryId?/:lang?",
      "example": "/followin",
      "parameters": {
        "categoryId": {
          "description": "Category ID",
          "options": [
            {
              "value": "1",
              "label": "For You"
            },
            {
              "value": "9",
              "label": "Market"
            },
            {
              "value": "13",
              "label": "Meme"
            },
            {
              "value": "14",
              "label": "BRC20"
            },
            {
              "value": "3",
              "label": "NFT"
            },
            {
              "value": "5",
              "label": "Thread"
            },
            {
              "value": "6",
              "label": "In-depth"
            },
            {
              "value": "8",
              "label": "Tutorials"
            },
            {
              "value": "11",
              "label": "Videos"
            }
          ],
          "default": "1"
        },
        "lang": {
          "description": "Language",
          "options": [
            {
              "value": "en",
              "label": "English"
            },
            {
              "value": "zh-Hans",
              "label": "简体中文"
            },
            {
              "value": "zh-Hant",
              "label": "繁體中文"
            },
            {
              "value": "vi",
              "label": "Tiếng Việt"
            }
          ],
          "default": "en"
        }
      },
      "description": "Category ID\n\n| For You | Market | Meme | BRC20 | NFT | Thread | In-depth | Tutorials | Videos |\n| ------- | ------ | ---- | ----- | --- | ------ | -------- | --------- | ------ |\n| 1       | 9      | 13   | 14    | 3   | 5      | 6        | 8         | 11     |\n\n  Language\n\n| English | 简体中文 | 繁體中文 | Tiếng Việt |\n| ------- | -------- | -------- | ---------- |\n| en      | zh-Hans  | zh-Hant  | vi         |"
    }
  },
  {
    "provider_id": "foresightnews",
    "provider_name": "Foresight News",
    "route_key": "/",
    "route": {
      "name": "精选资讯",
      "path": "/",
      "example": "/foresightnews",
      "parameters": {},
      "description": ""
    }
  },
  {
    "provider_id": "furaffinity",
    "provider_name": "Furaffinity",
    "route_key": "/home/:category/:mode?",
    "route": {
      "name": "Home",
      "path": "/home/:category/:mode?",
      "example": "/furaffinity/home/nsfw",
      "parameters": {
        "category": "Category, default value is artwork, options are artwork, writing, music, crafts",
        "mode": "R18 content toggle, default value is sfw, options are sfw, nsfw"
      },
      "description": ""
    }
  },
  {
    "provider_id": "gamer",
    "provider_name": "巴哈姆特電玩資訊站",
    "route_key": "/ani/anime/:sn",
    "route": {
      "name": "動畫瘋 - 動畫",
      "path": "/ani/anime/:sn",
      "example": "/gamer/ani/anime/36868",
      "parameters": {
        "sn": "動畫 sn，在 URL 可以找到"
      },
      "description": ""
    }
  },
  {
    "provider_id": "gamer",
    "provider_name": "巴哈姆特電玩資訊站",
    "route_key": "/ani/new_anime",
    "route": {
      "name": "動畫瘋 - 最後更新",
      "path": "/ani/new_anime",
      "example": "/gamer/ani/new_anime",
      "parameters": {},
      "description": ""
    }
  },
  {
    "provider_id": "gcores",
    "provider_name": "机核网",
    "route_key": "/radios/:category?",
    "route": {
      "name": "播客",
      "path": "/radios/:category?",
      "example": "/gcores/radios/45",
      "parameters": {
        "category": "分类名，默认为全部，可在分类页面的 URL 中找到，如 Gadio News -- 45"
      },
      "description": ""
    }
  },
  {
    "provider_id": "gelonghui",
    "provider_name": "格隆汇",
    "route_key": "/home/:tag?",
    "route": {
      "name": "首页",
      "path": "/home/:tag?",
      "example": "/gelonghui/home",
      "parameters": {
        "tag": {
          "description": "分类标签，见下表，默认为 `web_home_page`",
          "options": [
            {
              "value": "web_home_page",
              "label": "推荐"
            },
            {
              "value": "stock",
              "label": "股票"
            },
            {
              "value": "fund",
              "label": "基金"
            },
            {
              "value": "new_stock",
              "label": "新股"
            },
            {
              "value": "research",
              "label": "研报"
            }
          ]
        }
      },
      "description": "| 推荐            | 股票  | 基金 | 新股       | 研报     |\n| --------------- | ----- | ---- | ---------- | -------- |\n| web_home_page | stock | fund | new_stock | research |"
    }
  },
  {
    "provider_id": "gelonghui",
    "provider_name": "格隆汇",
    "route_key": "/user/:id",
    "route": {
      "name": "用户文章",
      "path": "/user/:id",
      "example": "/gelonghui/user/5273",
      "parameters": {
        "id": "用户编号，可在用户页 URL 中找到"
      },
      "description": ""
    }
  },
  {
    "provider_id": "github",
    "provider_name": "GitHub",
    "route_key": "/activity/:user",
    "route": {
      "name": "User Activities",
      "path": "/activity/:user",
      "example": "/github/activity/DIYgod",
      "parameters": {
        "user": "GitHub username"
      },
      "description": "Get the activities of a user on GitHub, based on the GitHub official RSS feed"
    }
  },
  {
    "provider_id": "google",
    "provider_name": "Google",
    "route_key": "/doodles/:language?",
    "route": {
      "name": "Update",
      "path": "/doodles/:language?",
      "example": "/google/doodles/zh-CN",
      "parameters": {
        "language": "Language, default to `zh-CN`, for other language values, you can get it from [Google Doodles official website](https://www.google.com/doodles)"
      },
      "description": ""
    }
  },
  {
    "provider_id": "grist",
    "provider_name": "Grist",
    "route_key": "/",
    "route": {
      "name": "Latest Articles",
      "path": "/",
      "example": "/grist",
      "parameters": {},
      "description": ""
    }
  },
  {
    "provider_id": "grist",
    "provider_name": "Grist",
    "route_key": "/series/:series",
    "route": {
      "name": "Series",
      "path": "/series/:series",
      "example": "/grist/series/best-of-grist",
      "parameters": {
        "series": "Find in the URL which has /series/"
      },
      "description": ""
    }
  },
  {
    "provider_id": "guokr",
    "provider_name": "果壳网",
    "route_key": "/column/:channel",
    "route": {
      "name": "果壳网专栏",
      "path": "/column/:channel",
      "example": "/guokr/column/calendar",
      "parameters": {
        "channel": "专栏类别"
      },
      "description": "| 物种日历 | 吃货研究所 | 美丽也是技术活 |\n| -------- | ---------- | -------------- |\n| calendar | institute  | beauty         |"
    }
  },
  {
    "provider_id": "guokr",
    "provider_name": "果壳网",
    "route_key": "/scientific",
    "route": {
      "name": "科学人",
      "path": "/scientific",
      "example": "/guokr/scientific",
      "parameters": {},
      "description": ""
    }
  },
  {
    "provider_id": "hackernews",
    "provider_name": "Hacker News",
    "route_key": "/:section?/:type?/:user?",
    "route": {
      "name": "User",
      "path": "/:section?/:type?/:user?",
      "example": "/hackernews/threads/comments_list/dang",
      "parameters": {
        "section": {
          "description": "Content section, default to `index`"
        },
        "type": {
          "description": "Link type, default to `sources`"
        },
        "user": {
          "description": "Set user, only valid in `threads` and `submitted` sections"
        }
      },
      "description": "Subscribe to the content of a specific user"
    }
  },
  {
    "provider_id": "hellobtc",
    "provider_name": "白话区块链",
    "route_key": "/news",
    "route": {
      "name": "快讯",
      "path": "/news",
      "example": "/hellobtc/news",
      "parameters": {},
      "description": ""
    }
  },
  {
    "provider_id": "huxiu",
    "provider_name": "虎嗅",
    "route_key": "/collection/:id",
    "route": {
      "name": "文集",
      "path": "/collection/:id",
      "example": "/huxiu/collection/212",
      "parameters": {
        "id": "文集 id，可在对应文集页 URL 中找到"
      },
      "description": "更多文集请参见 [文集](https://www.huxiu.com/collection)"
    }
  },
  {
    "provider_id": "huxiu",
    "provider_name": "虎嗅",
    "route_key": "/search/:keyword",
    "route": {
      "name": "搜索",
      "path": "/search/:keyword",
      "example": "/huxiu/search/生活",
      "parameters": {
        "keyword": "关键字"
      },
      "description": ""
    }
  },
  {
    "provider_id": "huxiu",
    "provider_name": "虎嗅",
    "route_key": "/tag/:id",
    "route": {
      "name": "标签",
      "path": "/tag/:id",
      "example": "/huxiu/tag/291",
      "parameters": {
        "id": "标签 id，可在对应标签页 URL 中找到"
      },
      "description": "更多标签请参见 [标签](https://www.huxiu.com/tags)"
    }
  },
  {
    "provider_id": "idolypride",
    "provider_name": "IDOLY PRIDE 偶像荣耀",
    "route_key": "/news",
    "route": {
      "name": "News",
      "path": "/news",
      "example": "/idolypride/news",
      "parameters": {},
      "description": ""
    }
  },
  {
    "provider_id": "ifanr",
    "provider_name": "爱范儿",
    "route_key": "/digest",
    "route": {
      "name": "快讯",
      "path": "/digest",
      "example": "/ifanr/digest",
      "parameters": {},
      "description": ""
    }
  },
  {
    "provider_id": "imdb",
    "provider_name": "IMDb",
    "route_key": "/chart/:chart?",
    "route": {
      "name": "Charts",
      "path": "/chart/:chart?",
      "example": "/imdb/chart",
      "parameters": {
        "chart": {
          "description": "The chart to display, `top` by default",
          "options": [
            {
              "value": "top",
              "label": "Top 250 Movies"
            },
            {
              "value": "moviemeter",
              "label": "Most Popular Movies"
            },
            {
              "value": "toptv",
              "label": "Top 250 TV Shows"
            },
            {
              "value": "tvmeter",
              "label": "Most Popular TV Shows"
            }
          ],
          "default": "top"
        }
      },
      "description": "| Top 250 Movies | Most Popular Movies | Top 250 TV Shows | Most Popular TV Shows |\n| -------------- | ------------------- | ---------------- | --------------------- |\n| top            | moviemeter          | toptv            | tvmeter               |"
    }
  },
  {
    "provider_id": "infoq",
    "provider_name": "InfoQ 中文",
    "route_key": "/presentations/:conference?",
    "route": {
      "name": "Presentations",
      "path": "/presentations/:conference?",
      "example": "/infoq/presentations",
      "parameters": {
        "conference": "Conference, all by default, can be found in URL"
      },
      "description": "::: tip\n  If you subscribe to [InfoQ Live Jan 2024](https://www.infoq.com/infoq-live-jan-2024/presentations/)，where the URL is `https://www.infoq.com/infoq-live-jan-2024/presentations/`, extract the part `https://www.infoq.com/` to the end, which is `/presentations/`, and use it as the parameter to fill in. Therefore, the route will be [`/infoq/presentations/infoq-live-jan-2024`](https://rsshub.app/infoq/presentations/infoq-live-jan-2024).\n:::\n    "
    }
  },
  {
    "provider_id": "inoreader",
    "provider_name": "Inoreader",
    "route_key": "/rss/:user/:tag",
    "route": {
      "name": "RSS",
      "path": "/rss/:user/:tag",
      "example": "/inoreader/rss/1005137674/user-favorites",
      "parameters": {
        "user": "user id, the interger after user/ in the example URL",
        "tag": "tag, the string after tag/ in the example URL"
      },
      "description": ""
    }
  },
  {
    "provider_id": "jianshu",
    "provider_name": "简书",
    "route_key": "/home",
    "route": {
      "name": "首页",
      "path": "/home",
      "example": "/jianshu/home",
      "parameters": {},
      "description": ""
    }
  },
  {
    "provider_id": "jike",
    "provider_name": "即刻",
    "route_key": "/topic/:id/:showUid?",
    "route": {
      "name": "圈子",
      "path": "/topic/:id/:showUid?",
      "example": "/jike/topic/556688fae4b00c57d9dd46ee",
      "parameters": {
        "id": "圈子 id, 可在即刻 web 端圈子页或 APP 分享出来的圈子页 URL 中找到",
        "showUid": {
          "description": "是否在内容中显示用户信息，设置为 1 则开启",
          "options": [
            {
              "value": "1",
              "label": "显示"
            }
          ]
        }
      },
      "description": ""
    }
  },
  {
    "provider_id": "jike",
    "provider_name": "即刻",
    "route_key": "/user/:id",
    "route": {
      "name": "用户动态",
      "path": "/user/:id",
      "example": "/jike/user/3EE02BC9-C5B3-4209-8750-4ED1EE0F67BB",
      "parameters": {
        "id": "用户 id, 可在即刻分享出来的单条动态页点击用户头像进入个人主页，然后在个人主页的 URL 中找到，或者在单条动态页使用 RSSHub Radar 插件"
      },
      "description": ""
    }
  },
  {
    "provider_id": "jin10",
    "provider_name": "金十数据",
    "route_key": "/:important?",
    "route": {
      "name": "市场快讯",
      "path": "/:important?",
      "example": "/jin10",
      "parameters": {
        "important": "只看重要，任意值开启，留空关闭"
      },
      "description": ""
    }
  },
  {
    "provider_id": "jinse",
    "provider_name": "金色财经",
    "route_key": "/lives/:category?",
    "route": {
      "name": "快讯",
      "path": "/lives/:category?",
      "example": "/jinse/lives",
      "parameters": {
        "category": {
          "description": "分类",
          "options": [
            {
              "value": "0",
              "label": "全部"
            },
            {
              "value": "1",
              "label": "精选"
            },
            {
              "value": "2",
              "label": "政策"
            },
            {
              "value": "3",
              "label": "数据"
            },
            {
              "value": "4",
              "label": "NFT"
            },
            {
              "value": "5",
              "label": "项目"
            }
          ],
          "default": "0"
        }
      },
      "description": "| 全部 | 精选 | 政策 | 数据 | NFT | 项目 |\n| ---- | ---- | ---- | ---- | --- | ---- |\n| 0    | 1    | 2    | 3    | 4   | 5    |"
    }
  },
  {
    "provider_id": "laohu8",
    "provider_name": "老虎社区",
    "route_key": "/personal/:id",
    "route": {
      "name": "个人主页",
      "path": "/personal/:id",
      "example": "/laohu8/personal/3527667596890271",
      "parameters": {
        "id": "用户 ID，见网址链接"
      },
      "description": ""
    }
  },
  {
    "provider_id": "linkedin",
    "provider_name": "LinkedIn",
    "route_key": "/jobs/:job_types/:exp_levels/:keywords?/:routeParams?",
    "route": {
      "name": "Jobs",
      "path": "/jobs/:job_types/:exp_levels/:keywords?/:routeParams?",
      "example": "/linkedin/jobs/C-P/1/software engineer",
      "parameters": {
        "job_types": "See the following table for details, use '-' as delimiter",
        "exp_levels": "See the following table for details, use '-' as delimiter",
        "keywords": "keywords",
        "routeParams": "additional query parameters, see the table below"
      },
      "description": "#### `job_types` list\n\n| Full Time | Part Time | Contractor | All |\n| --------- | --------- | ---------- | --- |\n| F         | P         | C          | all |\n\n#### `exp_levels` list\n\n| Intership | Entry Level | Associate | Mid-Senior Level | Director | All |\n| --------- | ----------- | --------- | ---------------- | -------- | --- |\n| 1         | 2           | 3         | 4                | 5        | all |\n\n#### `routeParams` additional query parameters\n\n##### `f_WT` list\n\n| Onsite | Remote | Hybrid |\n| ------ | ------- | ------ |\n|    1   |    2    |   3    |\n\n##### `geoId`\n\n  Geographic location ID. You can find this ID in the URL of a LinkedIn job search page that is filtered by location.\n\n  For example:\n  91000012 is the ID of East Asia.\n\n##### `f_TPR`\n\n  Time posted range. Here are some possible values:\n\n  *   `r86400`: Past 24 hours\n  *   `r604800`: Past week\n  *   `r2592000`: Past month\n\n  For example:\n\n  1.  If we want to search software engineer jobs of all levels and all job types, use `/linkedin/jobs/all/all/software engineer`\n  2.  If we want to search all entry level contractor/part time software engineer jobs, use `/linkedin/jobs/P-C/2/software engineer`\n  3.  If we want to search remote mid-senior level software engineer jobs in APAC posted within the last month, use `/linkedin/jobs/F/4/software%20engineer/f_WT=2&geoId=91000003&f_TPR=r2592000`\n\n  **To make it easier, the recommended way is to start a search on [LinkedIn](https://www.linkedin.com/jobs/search) and use [RSSHub Radar](https://github.com/DIYgod/RSSHub-Radar) to load the specific feed.**"
    }
  },
  {
    "provider_id": "liveuamap",
    "provider_name": "Live Universal Awareness Map",
    "route_key": "/:region?",
    "route": {
      "name": "实时消息",
      "path": "/:region?",
      "example": "/liveuamap",
      "parameters": {
        "region": "region 热点地区，默认为`ukraine`，其他选项见liveuamap.com的三级域名"
      },
      "description": ""
    }
  },
  {
    "provider_id": "lofter",
    "provider_name": "Lofter",
    "route_key": "/tag/:name?/:type?",
    "route": {
      "name": "Tag",
      "path": "/tag/:name?/:type?",
      "example": "/lofter/tag/cosplay/date",
      "parameters": {
        "name": "tag name, such as `名侦探柯南`, `摄影` by default",
        "type": "ranking type, see below, new by default"
      },
      "description": "| new  | date | week | month | total |\n| ---- | ---- | ---- | ----- | ----- |\n| 最新 | 日榜 | 周榜 | 月榜  | 总榜  |"
    }
  },
  {
    "provider_id": "macfilos",
    "provider_name": "Macfilos",
    "route_key": "/blog",
    "route": {
      "name": "Blog",
      "path": "/blog",
      "example": "/macfilos/blog",
      "parameters": {},
      "description": ""
    }
  },
  {
    "provider_id": "mirror",
    "provider_name": "Mirror",
    "route_key": "/:id",
    "route": {
      "name": "User",
      "path": "/:id",
      "example": "/mirror/tingfei.eth",
      "parameters": {
        "id": "user id"
      },
      "description": ""
    }
  },
  {
    "provider_id": "misskey",
    "provider_name": "Misskey",
    "route_key": "/notes/featured/:site",
    "route": {
      "name": "Featured Notes",
      "path": "/notes/featured/:site",
      "example": "/misskey/notes/featured/misskey.io",
      "parameters": {
        "site": "instance address, domain only, without `http://` or `https://` protocol header"
      },
      "description": ""
    }
  },
  {
    "provider_id": "misskey",
    "provider_name": "Misskey",
    "route_key": "/users/notes/:username/:routeParams?",
    "route": {
      "name": "User timeline",
      "path": "/users/notes/:username/:routeParams?",
      "example": "/misskey/users/notes/support@misskey.io",
      "parameters": {
        "username": "Misskey username in the format of username@instance.domain",
        "routeParams": "\n| Key               | Description                             | Accepted Values | Default |\n| ----------------- | --------------------------------------- | --------------- | ------- |\n| withRenotes       | Include renotes in the timeline         | 0/1/true/false  | false   |\n| mediaOnly         | Only return posts containing media      | 0/1/true/false  | false   |\n| simplifyAuthor    | Simplify author field in feed items     | 0/1/true/false  | false   |\n\nNote: `withRenotes` and `mediaOnly` are mutually exclusive and cannot both be set to true.\n\nExamples:\n- /misskey/users/notes/mttb2ccp@misskey.io/withRenotes=true\n- /misskey/users/notes/mttb2ccp@misskey.io/mediaOnly=true"
      },
      "description": ""
    }
  },
  {
    "provider_id": "mygopen",
    "provider_name": "MyGoPen",
    "route_key": "/:label?",
    "route": {
      "name": "分類",
      "path": "/:label?",
      "example": "/mygopen",
      "parameters": {
        "label": "分類，见下表，默认为首页"
      },
      "description": "| 謠言 | 詐騙 | 真實資訊 | 教學 |\n| ---- | ---- | -------- | ---- |"
    }
  },
  {
    "provider_id": "nautil",
    "provider_name": "Nautilus",
    "route_key": "/topic/:tid",
    "route": {
      "name": "Topics",
      "path": "/topic/:tid",
      "example": "/nautil/topic/arts",
      "parameters": {
        "tid": "topic"
      },
      "description": "This route provides a flexible plan with full text content to subscribe specific topic(s) on the Nautilus. Please visit [nautil.us](https://nautil.us) and click `Topics` to acquire whole topic list."
    }
  },
  {
    "provider_id": "notefolio",
    "provider_name": "Notefolio",
    "route_key": "/search/:category?/:order?/:time?/:query?",
    "route": {
      "name": "Works",
      "path": "/search/:category?/:order?/:time?/:query?",
      "example": "/notefolio/search/1/pick/all/life",
      "parameters": {
        "category": {
          "description": "Category, see below",
          "options": [
            {
              "value": "all",
              "label": "All (전체)"
            },
            {
              "value": "1",
              "label": "Video / Motion Graphics (영상/모션그래픽)"
            },
            {
              "value": "2",
              "label": "Graphic Design (그래픽 디자인)"
            },
            {
              "value": "3",
              "label": "Branding / Editing (브랜딩/편집)"
            },
            {
              "value": "4",
              "label": "UI/UX (UI/UX)"
            },
            {
              "value": "5",
              "label": "Illustration (일러스트레이션)"
            },
            {
              "value": "6",
              "label": "Digital Art (디지털 아트)"
            },
            {
              "value": "7",
              "label": "Character Design (캐릭터 디자인)"
            },
            {
              "value": "8",
              "label": "Product Package Design (제품/패키지 디자인)"
            },
            {
              "value": "9",
              "label": "Photography (포토그래피)"
            },
            {
              "value": "10",
              "label": "Typography (타이포그래피)"
            },
            {
              "value": "11",
              "label": "Crafts (공예)"
            },
            {
              "value": "12",
              "label": "Fine Art (파인아트)"
            }
          ],
          "default": "all"
        },
        "order": {
          "description": "Order, `pick` as Notefolio Pick, `published` as Newest, `like` as like, `pick` by default",
          "options": [
            {
              "value": "pick",
              "label": "Notefolio Pick"
            },
            {
              "value": "published",
              "label": "Newest"
            },
            {
              "value": "like",
              "label": "Like"
            }
          ],
          "default": "pick"
        },
        "time": {
          "description": "Time",
          "options": [
            {
              "value": "all",
              "label": "All the time"
            },
            {
              "value": "one-day",
              "label": "Latest 24 hours"
            },
            {
              "value": "week",
              "label": "Latest week"
            },
            {
              "value": "month",
              "label": "Latest month"
            },
            {
              "value": "three-month",
              "label": "Latest 3 months"
            }
          ],
          "default": "all"
        },
        "query": "Keyword, empty by default"
      },
      "description": "| Category | Name in Korean     | Name in English         |\n| -------- | ------------------ | ----------------------- |\n| all      | 전체               | All                     |\n| 1        | 영상/모션그래픽    | Video / Motion Graphics |\n| 2        | 그래픽 디자인      | Graphic Design          |\n| 3        | 브랜딩/편집        | Branding / Editing      |\n| 4        | UI/UX              | UI/UX                   |\n| 5        | 일러스트레이션     | Illustration            |\n| 6        | 디지털 아트        | Digital Art             |\n| 7        | 캐릭터 디자인      | Character Design        |\n| 8        | 제품/패키지 디자인 | Product Package Design  |\n| 9        | 포토그래피         | Photography             |\n| 10       | 타이포그래피       | Typography              |\n| 11       | 공예               | Crafts                  |\n| 12       | 파인아트           | Fine Art                |"
    }
  },
  {
    "provider_id": "nytimes",
    "provider_name": "The New York Times",
    "route_key": "/book/:category?",
    "route": {
      "name": "Best Seller Books",
      "path": "/book/:category?",
      "example": "/nytimes/book/combined-print-and-e-book-nonfiction",
      "parameters": {
        "category": {
          "description": "Category, can be found on the [official page](https://www.nytimes.com/books/best-sellers/)",
          "options": [
            {
              "value": "combined-print-and-e-book-nonfiction",
              "label": "Combined Print & E-Book Nonfiction"
            },
            {
              "value": "hardcover-nonfiction",
              "label": "Hardcover Nonfiction"
            },
            {
              "value": "paperback-nonfiction",
              "label": "Paperback Nonfiction"
            },
            {
              "value": "advice-how-to-and-miscellaneous",
              "label": "Advice, How-To & Miscellaneous"
            },
            {
              "value": "combined-print-and-e-book-fiction",
              "label": "Combined Print & E-Book Fiction"
            },
            {
              "value": "hardcover-fiction",
              "label": "Hardcover Fiction"
            },
            {
              "value": "trade-fiction-paperback",
              "label": "Paperback Trade Fiction"
            },
            {
              "value": "childrens-middle-grade-hardcover",
              "label": "Children's Middle Grade Hardcover"
            },
            {
              "value": "picture-books",
              "label": "Picture Books"
            },
            {
              "value": "series-books",
              "label": "Series Books"
            },
            {
              "value": "young-adult-hardcover",
              "label": "Young Adult Hardcover"
            }
          ],
          "default": "combined-print-and-e-book-nonfiction"
        }
      },
      "description": ""
    }
  },
  {
    "provider_id": "nytimes",
    "provider_name": "The New York Times",
    "route_key": "/:lang?",
    "route": {
      "name": "News",
      "path": "/:lang?",
      "example": "/nytimes/dual",
      "parameters": {
        "lang": {
          "description": "language, default to Chinese",
          "options": [
            {
              "value": "dual",
              "label": "Chinese-English"
            },
            {
              "value": "en",
              "label": "English"
            },
            {
              "value": "traditionalchinese",
              "label": "Traditional Chinese"
            },
            {
              "value": "dual-traditionalchinese",
              "label": "Chinese-English (Traditional Chinese)"
            }
          ]
        }
      },
      "description": "By extracting the full text of articles, we provide a better reading experience (full text articles) over the official one."
    }
  },
  {
    "provider_id": "odaily",
    "provider_name": "Odaily 星球日报",
    "route_key": "/newsflash",
    "route": {
      "name": "快讯",
      "path": "/newsflash",
      "example": "/odaily/newsflash",
      "parameters": {},
      "description": ""
    }
  },
  {
    "provider_id": "odaily",
    "provider_name": "Odaily 星球日报",
    "route_key": "/search/news/:keyword",
    "route": {
      "name": "搜索快讯",
      "path": "/search/news/:keyword",
      "example": "/odaily/search/news/RSS3",
      "parameters": {
        "keyword": "搜索关键字"
      },
      "description": ""
    }
  },
  {
    "provider_id": "pingwest",
    "provider_name": "品玩",
    "route_key": "/status",
    "route": {
      "name": "实时要闻",
      "path": "/status",
      "example": "/pingwest/status",
      "parameters": {},
      "description": ""
    }
  },
  {
    "provider_id": "pixivision",
    "provider_name": "pixivision",
    "route_key": "/:lang/:category?",
    "route": {
      "name": "Category",
      "path": "/:lang/:category?",
      "example": "/pixivision/zh-tw",
      "parameters": {
        "lang": "Language",
        "category": "Category"
      },
      "description": "::: tip\n  `https://www.pixivision.net/zh-tw/c/interview` → `/pixivision/zh-tw/interview`\n:::"
    }
  },
  {
    "provider_id": "plurk",
    "provider_name": "Plurk",
    "route_key": "/anonymous",
    "route": {
      "name": "Anonymous",
      "path": "/anonymous",
      "example": "/plurk/anonymous",
      "parameters": {},
      "description": ""
    }
  },
  {
    "provider_id": "plurk",
    "provider_name": "Plurk",
    "route_key": "/topic/:topic",
    "route": {
      "name": "Topic",
      "path": "/topic/:topic",
      "example": "/plurk/topic/standwithukraine",
      "parameters": {
        "topic": "Topic ID, can be found in URL"
      },
      "description": ""
    }
  },
  {
    "provider_id": "plurk",
    "provider_name": "Plurk",
    "route_key": "/user/:user",
    "route": {
      "name": "User",
      "path": "/user/:user",
      "example": "/plurk/user/plurkoffice",
      "parameters": {
        "user": "User ID, can be found in URL"
      },
      "description": ""
    }
  },
  {
    "provider_id": "podwise",
    "provider_name": "Podwise",
    "route_key": "/explore",
    "route": {
      "name": "Collections",
      "path": "/explore",
      "example": "/podwise/explore",
      "parameters": {},
      "description": ""
    }
  },
  {
    "provider_id": "pornhub",
    "provider_name": "PornHub",
    "route_key": "/category/:caty",
    "route": {
      "name": "Category",
      "path": "/category/:caty",
      "example": "/pornhub/category/popular-with-women",
      "parameters": {
        "caty": "category, see [categories](https://www.pornhub.com/webmasters/categories)"
      },
      "description": ""
    }
  },
  {
    "provider_id": "simpleinfo",
    "provider_name": "簡訊設計",
    "route_key": "/:category?",
    "route": {
      "name": "志祺七七",
      "path": "/:category?",
      "example": "/simpleinfo",
      "parameters": {
        "category": "分类名"
      },
      "description": "| 夥伴聊聊 | 專案設計 |\n| -------- | -------- |\n| work     | talk     |\n\n| 國內外新聞 | 政治百分百 | 社會觀察家 | 心理與哲學            |\n| ---------- | ---------- | ---------- | --------------------- |\n| news       | politics   | society    | psychology-philosophy |\n\n| 科學大探索 | 環境與健康         | ACG 快樂聊 | 好書籍分享   | 其它主題     |\n| ---------- | ------------------ | ---------- | ------------ | ------------ |\n| science    | environment-health | acg        | book-sharing | other-topics |"
    }
  },
  {
    "provider_id": "smzdm",
    "provider_name": "什么值得买",
    "route_key": "/ranking/:rank_type/:rank_id/:hour",
    "route": {
      "name": "排行榜",
      "path": "/ranking/:rank_type/:rank_id/:hour",
      "example": "/smzdm/ranking/pinlei/11/3",
      "parameters": {
        "rank_type": {
          "description": "榜单类型",
          "options": [
            {
              "value": "pinlei",
              "label": "好价品类榜"
            },
            {
              "value": "dianshang",
              "label": "好价电商榜"
            },
            {
              "value": "haitao",
              "label": "海淘 TOP 榜"
            },
            {
              "value": "haowen",
              "label": "好文排行榜"
            },
            {
              "value": "haowu",
              "label": "好物排行榜"
            }
          ]
        },
        "rank_id": {
          "description": "榜单ID",
          "options": [
            {
              "label": "好价品类榜 - 全部",
              "value": "11"
            },
            {
              "label": "好价品类榜 - 食品生鲜",
              "value": "12"
            },
            {
              "label": "好价品类榜 - 电脑数码",
              "value": "13"
            },
            {
              "label": "好价品类榜 - 运动户外",
              "value": "14"
            },
            {
              "label": "好价品类榜 - 家用电器",
              "value": "15"
            },
            {
              "label": "好价品类榜 - 白菜",
              "value": "17"
            },
            {
              "label": "好价品类榜 - 服饰鞋包",
              "value": "74"
            },
            {
              "label": "好价品类榜 - 日用百货",
              "value": "75"
            },
            {
              "label": "好价电商榜 - 券活动",
              "value": "24"
            },
            {
              "label": "好价电商榜 - 京东",
              "value": "23"
            },
            {
              "label": "好价电商榜 - 天猫",
              "value": "25"
            },
            {
              "label": "好价电商榜 - 亚马逊中国",
              "value": "26"
            },
            {
              "label": "好价电商榜 - 国美在线",
              "value": "27"
            },
            {
              "label": "好价电商榜 - 苏宁易购",
              "value": "28"
            },
            {
              "label": "好价电商榜 - 网易",
              "value": "29"
            },
            {
              "label": "好价电商榜 - 西集网",
              "value": "30"
            },
            {
              "label": "好价电商榜 - 美国亚马逊",
              "value": "31"
            },
            {
              "label": "好价电商榜 - 日本亚马逊",
              "value": "32"
            },
            {
              "label": "好价电商榜 - ebay",
              "value": "33"
            },
            {
              "label": "海淘 TOP 榜 - 全部",
              "value": "39"
            },
            {
              "label": "海淘 TOP 榜 - 海外直邮",
              "value": "34"
            },
            {
              "label": "海淘 TOP 榜 - 美国榜",
              "value": "35"
            },
            {
              "label": "海淘 TOP 榜 - 欧洲榜",
              "value": "36"
            },
            {
              "label": "海淘 TOP 榜 - 澳新榜",
              "value": "37"
            },
            {
              "label": "海淘 TOP 榜 - 亚洲榜",
              "value": "38"
            },
            {
              "label": "海淘 TOP 榜 - 晒物榜",
              "value": "hsw"
            },
            {
              "label": "好文排行榜 - 原创",
              "value": "yc"
            },
            {
              "label": "好文排行榜 - 资讯",
              "value": "zx"
            },
            {
              "label": "好物排行榜 - 新晋榜",
              "value": "hwall"
            },
            {
              "label": "好物排行榜 - 消费众测",
              "value": "zc"
            },
            {
              "label": "好物排行榜 - 新锐品牌",
              "value": "nb"
            },
            {
              "label": "好物排行榜 - 好物榜单",
              "value": "hw"
            }
          ]
        },
        "hour": {
          "description": "时间跨度",
          "options": [
            {
              "value": "3",
              "label": "3 小时"
            },
            {
              "value": "12",
              "label": "12 小时"
            },
            {
              "value": "24",
              "label": "24 小时"
            }
          ]
        }
      },
      "description": ""
    }
  },
  {
    "provider_id": "solidot",
    "provider_name": "Solidot",
    "route_key": "/:type?",
    "route": {
      "name": "最新消息",
      "path": "/:type?",
      "example": "/solidot/linux",
      "parameters": {
        "type": {
          "description": "消息类型，在网站上方选择后复制子域名或参见 [https://www.solidot.org/index.rss](https://www.solidot.org/index.rss) 即可",
          "options": [
            {
              "value": "www",
              "label": "全部"
            },
            {
              "value": "startup",
              "label": "创业"
            },
            {
              "value": "linux",
              "label": "Linux"
            },
            {
              "value": "science",
              "label": "科学"
            },
            {
              "value": "technology",
              "label": "科技"
            },
            {
              "value": "mobile",
              "label": "移动"
            },
            {
              "value": "apple",
              "label": "苹果"
            },
            {
              "value": "hardware",
              "label": "硬件"
            },
            {
              "value": "software",
              "label": "软件"
            },
            {
              "value": "security",
              "label": "安全"
            },
            {
              "value": "games",
              "label": "游戏"
            },
            {
              "value": "books",
              "label": "书籍"
            },
            {
              "value": "ask",
              "label": "ask"
            },
            {
              "value": "idle",
              "label": "idle"
            },
            {
              "value": "blog",
              "label": "博客"
            },
            {
              "value": "cloud",
              "label": "云计算"
            },
            {
              "value": "story",
              "label": "奇客故事"
            }
          ],
          "default": "www"
        }
      },
      "description": ""
    }
  },
  {
    "provider_id": "sspai",
    "provider_name": "少数派 sspai",
    "route_key": "/index",
    "route": {
      "name": "首页",
      "path": "/index",
      "example": "/sspai/index",
      "parameters": {},
      "description": ""
    }
  },
  {
    "provider_id": "startuplatte",
    "provider_name": "創新拿鐵",
    "route_key": "/:category?",
    "route": {
      "name": "分类",
      "path": "/:category?",
      "example": "/startuplatte",
      "parameters": {
        "category": "分类，见下表，默认为首頁"
      },
      "description": "| 首頁 | 大師智慧 | 深度分析 | 新知介紹 |\n| ---- | -------- | -------- | -------- |\n|      | quote    | analysis | trend    |"
    }
  },
  {
    "provider_id": "stockedge",
    "provider_name": "Stock Edge",
    "route_key": "/daily-updates/news",
    "route": {
      "name": "Daily Updates News",
      "path": "/daily-updates/news",
      "example": "/stockedge/daily-updates/news",
      "parameters": {},
      "description": ""
    }
  },
  {
    "provider_id": "techflowpost",
    "provider_name": "深潮 TechFlow",
    "route_key": "/",
    "route": {
      "name": "首页",
      "path": "/",
      "example": "/techflowpost",
      "parameters": {},
      "description": ""
    }
  },
  {
    "provider_id": "telegram",
    "provider_name": "Telegram",
    "route_key": "/blog",
    "route": {
      "name": "Telegram Blog",
      "path": "/blog",
      "example": "/telegram/blog",
      "parameters": {},
      "description": ""
    }
  },
  {
    "provider_id": "telegram",
    "provider_name": "Telegram",
    "route_key": "/channel/:username/:routeParams?",
    "route": {
      "name": "Channel",
      "path": "/channel/:username/:routeParams?",
      "example": "/telegram/channel/awesomeRSSHub",
      "parameters": {
        "username": "channel username",
        "routeParams": "extra parameters, see the table below\n| Key                    | Description                                                           | Accepts                                            | Defaults to  |\n| :--------------------: | :-------------------------------------------------------------------: | :------------------------------------------------: | :----------: |\n| showLinkPreview        | Show the link preview from Telegram                                   | 0/1/true/false                                     | true         |\n| showViaBot             | For messages sent via bot, show the bot                               | 0/1/true/false                                     | true         |\n| showReplyTo            | For reply messages, show the target of the reply                      | 0/1/true/false                                     | true         |\n| showFwdFrom            | For forwarded messages, show the forwarding source                    | 0/1/true/false                                     | true         |\n| showFwdFromAuthor      | For forwarded messages, show the author of the forwarding source      | 0/1/true/false                                     | true         |\n| showInlineButtons      | Show inline buttons                                                   | 0/1/true/false                                     | false        |\n| showMediaTagInTitle    | Show media tags in the title                                          | 0/1/true/false                                     | true         |\n| showMediaTagAsEmoji    | Show media tags as emoji                                              | 0/1/true/false                                     | true         |\n| showHashtagAsHyperlink | Show hashtags as hyperlinks (`https://t.me/s/channel?q=%23hashtag`) | 0/1/true/false                                     | true         |\n| includeFwd             | Include forwarded messages                                            | 0/1/true/false                                     | true         |\n| includeReply           | Include reply messages                                                | 0/1/true/false                                     | true         |\n| includeServiceMsg      | Include service messages (e.g. message pinned, channel photo updated) | 0/1/true/false                                     | true         |\n| includeUnsupportedMsg  | Include messages unsupported by t.me                                  | 0/1/true/false                                     | false        |\n| searchQuery            | search query                                                          | keywords; replace `#hashtag` with `%23hashtag` | (no keyword) |\n\nSpecify different option values than default values can meet different needs, URL\n\n```\nhttps://rsshub.app/telegram/channel/NewlearnerChannel/showLinkPreview=0&showViaBot=0&showReplyTo=0&showFwdFrom=0&showFwdFromAuthor=0&showInlineButtons=0&showMediaTagInTitle=1&showMediaTagAsEmoji=1&includeFwd=0&includeReply=1&includeServiceMsg=0&includeUnsupportedMsg=0\n```\n\ngenerates an RSS without any link previews and annoying metadata, with emoji media tags in the title, without forwarded messages (but with reply messages), and without messages you don't care about (service messages and unsupported messages), for people who prefer pure subscriptions.\n\nFor backward compatibility reasons, invalid `routeParams` will be treated as `searchQuery` .\n"
      },
      "description": "\n::: tip\n  Due to Telegram restrictions, some channels involving pornography, copyright, and politics cannot be subscribed. You can confirm by visiting `https://t.me/s/:username`, it's recommended to deploy your own instance with telegram api configs (create your telegram application via `https://core.telegram.org/api/obtaining_api_id`, run this command `node ./lib/routes/telegram/scripts/get-telegram-session.mjs` to get `TELEGRAM_SESSION` and set it as Environment Variable).\n:::"
    }
  },
  {
    "provider_id": "thepaper",
    "provider_name": "澎湃新闻",
    "route_key": "/channel/:id",
    "route": {
      "name": "频道",
      "path": "/channel/:id",
      "example": "/thepaper/channel/25950",
      "parameters": {
        "id": "频道 id，可在频道页 URL 中找到"
      },
      "description": "| 频道 ID | 频道名 |\n| ------- | ------ |\n| 26916   | 视频   |\n| 108856  | 战疫   |\n| 25950   | 时事   |\n| 25951   | 财经   |\n| 36079   | 澎湃号 |\n| 119908  | 科技   |\n| 25952   | 思想   |\n| 119489  | 智库   |\n| 25953   | 生活   |\n| 26161   | 问吧   |\n| 122908  | 国际   |\n| -21     | 体育   |\n| -24     | 评论   |"
    }
  },
  {
    "provider_id": "thepaper",
    "provider_name": "澎湃新闻",
    "route_key": "/sidebar/:sec?",
    "route": {
      "name": "侧边栏",
      "path": "/sidebar/:sec?",
      "example": "/thepaper/sidebar",
      "parameters": {
        "sec": "侧边栏 id，可选 `hotNews` 即 澎湃热榜、`financialInformationNews` 即 澎湃财讯、`morningEveningNews` 即 早晚报，默认为 `hotNews`"
      },
      "description": ""
    }
  },
  {
    "provider_id": "tophub",
    "provider_name": "今日热榜",
    "route_key": "/list/:id",
    "route": {
      "name": "榜单列表",
      "path": "/list/:id",
      "example": "/tophub/list/Om4ejxvxEN",
      "parameters": {
        "id": "榜单id，可在 URL 中找到"
      },
      "description": "::: tip\n将榜单条目集合到一个列表中，可避免推送大量条目，更符合阅读习惯且有热度排序，推荐使用。\n:::"
    }
  },
  {
    "provider_id": "twitch",
    "provider_name": "Twitch",
    "route_key": "/live/:login",
    "route": {
      "name": "Live",
      "path": "/live/:login",
      "example": "/twitch/live/riotgames",
      "parameters": {
        "login": "Twitch username"
      },
      "description": ""
    }
  },
  {
    "provider_id": "twitter",
    "provider_name": "X (Twitter)",
    "route_key": "/keyword/:keyword/:routeParams?",
    "route": {
      "name": "Keyword",
      "path": "/keyword/:keyword/:routeParams?",
      "example": "/twitter/keyword/RSSHub",
      "parameters": {
        "keyword": "keyword",
        "routeParams": "extra parameters, see the table above"
      },
      "description": ""
    }
  },
  {
    "provider_id": "twreporter",
    "provider_name": "報導者",
    "route_key": "/newest",
    "route": {
      "name": "最新",
      "path": "/newest",
      "example": "/twreporter/newest",
      "parameters": {},
      "description": ""
    }
  },
  {
    "provider_id": "utgd",
    "provider_name": "UNTAG",
    "route_key": "/timeline",
    "route": {
      "name": "时间线",
      "path": "/timeline",
      "example": "/utgd/timeline",
      "parameters": {},
      "description": ""
    }
  },
  {
    "provider_id": "v2ex",
    "provider_name": "V2EX",
    "route_key": "/topics/:type",
    "route": {
      "name": "最热 / 最新主题",
      "path": "/topics/:type",
      "example": "/v2ex/topics/latest",
      "parameters": {
        "type": {
          "description": "主题类型",
          "options": [
            {
              "value": "hot",
              "label": "最热主题"
            },
            {
              "value": "latest",
              "label": "最新主题"
            }
          ],
          "default": "hot"
        }
      },
      "description": ""
    }
  },
  {
    "provider_id": "weibo",
    "provider_name": "微博",
    "route_key": "/keyword/:keyword/:routeParams?",
    "route": {
      "name": "关键词",
      "path": "/keyword/:keyword/:routeParams?",
      "example": "/weibo/keyword/RSSHub",
      "parameters": {
        "keyword": "你想订阅的微博关键词",
        "routeParams": "额外参数；请参阅上面的说明和表格"
      },
      "description": ""
    }
  },
  {
    "provider_id": "weibo",
    "provider_name": "微博",
    "route_key": "/search/hot/:fulltext?",
    "route": {
      "name": "热搜榜",
      "path": "/search/hot/:fulltext?",
      "example": "/weibo/search/hot",
      "parameters": {
        "fulltext": {
          "description": "\n-   使用`/weibo/search/hot`可以获取热搜条目列表；\n-   使用`/weibo/search/hot/fulltext`可以进一步获取热搜条目下的摘要信息（不含图片视频）；\n-   使用`/weibo/search/hot/fulltext?pic=true`可以获取图片缩略（但需要配合额外的手段，例如浏览器上的 Header Editor 等来修改 referer 参数为`https://weibo.com`，以规避微博的外链限制，否则图片无法显示。）\n-   使用`/weibo/search/hot/fulltext?pic=true&fullpic=true`可以获取 Original 图片（但需要配合额外的手段，例如浏览器上的 Header Editor 等来修改 referer 参数为`https://weibo.com`，以规避微博的外链限制，否则图片无法显示。）"
        }
      },
      "description": ""
    }
  },
  {
    "provider_id": "yahoo",
    "provider_name": "Yahoo",
    "route_key": "/news/providers/:region/list",
    "route": {
      "name": "新聞來源列表",
      "path": "/news/providers/:region/list",
      "example": "/yahoo/news/providers/tw/list",
      "parameters": {
        "region": "地区, 同路由\"新闻来源\"中的支持地区, 即 hk 或 tw"
      },
      "description": ""
    }
  },
  {
    "provider_id": "yande",
    "provider_name": "yande.re",
    "route_key": "/post/popular_recent/:period?",
    "route": {
      "name": "Popular Recent Posts",
      "path": "/post/popular_recent/:period?",
      "example": "/yande/post/popular_recent/1d",
      "parameters": {
        "period": {
          "description": "展示时间",
          "options": [
            {
              "value": "1d",
              "label": "最近 24 小时"
            },
            {
              "value": "1w",
              "label": "最近一周"
            },
            {
              "value": "1m",
              "label": "最近一月"
            },
            {
              "value": "1y",
              "label": "最近一年"
            }
          ],
          "default": "1d"
        }
      },
      "description": "| 最近 24 小时    | 最近一周     | 最近一月    | 最近一年     |\n| ------- | -------- | ------- | -------- |\n| 1d | 1w | 1m | 1y |"
    }
  }
]